rf_django_misc/__init__.py
rf_django_misc/test.py
rf_django_misc/drf/__init__.py
rf_django_misc/drf/middleware.py
rf_django_misc/management/__init__.py
rf_django_misc/management/commands/__init__.py
rf_django_misc/management/commands/set_site.py
rf_django_misc-0.2.0.dist-info/DESCRIPTION.rst
rf_django_misc-0.2.0.dist-info/METADATA
rf_django_misc-0.2.0.dist-info/RECORD
rf_django_misc-0.2.0.dist-info/WHEEL
rf_django_misc-0.2.0.dist-info/metadata.json
rf_django_misc-0.2.0.dist-info/top_level.txt
